{
    "add_configs": ["../roberta/small.json", "../base.json", "../downstream/downstream_small.json"],
    // "add_configs": ["../roberta/small.json", "../base.json"],
    // "eval_downstream": false,

    "tasks": {
        "gnn": {
            "task": "gnn",
            "arch": "encoder_gnn__roberta_small",

            "gnn_layer_type": "mlp_concat",
            "gnn_layer_args": {
                "enc_dim": 256,
                "layer_sizes": [[256, 2]],
                "n_gnn_layers": 1
            },
            "neg_type": "graph_text",
            "layer_sizes": [[256, 1], [1, 1]],
            "min_common_neighbors": 10,
            "max_common_neighbors": 10,
            "max_entities_size": 600,
            "max_entities_from_queue": 5,
            "num_text_chunks": 8,
            "min_common_neighbors_for_the_last_edge": 1,

            "non_mask_rate": 0,
            "subsampling_strategy": "by_entity_pair",
            "subsampling_cap": 100,
            "n_valid_examples": 400,

            "update_freq": 21,
            "epoch_size": 6e3,
            "max_sentences": 1,
            "max_tokens": 19000,

            "criterion": "cross_entropy_custom",
            "weight": 0.1
        },
        "mtb": {
            "task": "mtb",
            "arch": "encoder_mtb__roberta_small",
            "k_weak_negs": 100,
            "n_tries_entity": 100,
            "non_mask_rate": 0.7,
            "subsampling_strategy": "by_entity_pair",
            "subsampling_cap": 100,
            "n_valid_examples": 20000,

            "update_freq": 6,
            "epoch_size": 132000,
            "max_sentences": 77,
            "max_tokens": 1e4,

            "criterion": "cross_entropy_custom",
            "weight": 0.4
        },
        "mlm": {
            "task": "masked_lm_em",
            "non_mask_rate": 0.5,

            "mask_prob": 0.15,
            "leave_unmasked_prob": 0.1,
            "random_token_prob": 0.1,
            "freq_weighted_replacement": false,
            "mask_whole_words": true,

            "update_freq": 6,
            "epoch_size": 132000,
            "n_valid_examples": 20000,

            "max_sentences": 77,
            "max_tokens": 1e4,

            "criterion": "masked_lm_custom",
            "weight": 0.5
        }
    },

    "task": "multi_task",
    "arch": "multi_model",
    "use_sentence_negatives": false,
    "entity_dim": 256,
    "triplet_type": "concat_linear_dot",
    "encoder_output_layer_type": "entity_start_linear",

    // "data_path": "../data/nki/bin-v5-threshold20-small",
    "data_path": "../data/nki/bin-v5-threshold20",

    "mask_type": "start_end",

    "max_epoch": 200,
    "warmup_updates": 1000,
    "total_num_updates": 10000000,
    "lr": [2e-4],

    "num_workers": 0,
    "max_sentences": 1336,
    "update_freq": null,
    "max_tokens": 12000,
    "validate_before_training": false
}
